seed_phrases_for_kin/__init__.py
seed_phrases_for_kin/electrum_mnemonic.py
seed_phrases_for_kin/key_derivation.py
seed_phrases_for_kin/old_electrum_mnemonic.py
seed_phrases_for_kin/seed_phrase_to_kin_keys.py
seed_phrases_for_kin/version.py
seed_phrases_for_kin-0.2.dist-info/LICENSE
seed_phrases_for_kin-0.2.dist-info/METADATA
seed_phrases_for_kin-0.2.dist-info/WHEEL
seed_phrases_for_kin-0.2.dist-info/entry_points.txt
seed_phrases_for_kin-0.2.dist-info/top_level.txt
seed_phrases_for_kin-0.2.dist-info/RECORD
