Metadata-Version: 2.1
Name: seed-phrases-for-kin
Version: 0.2
Summary: Utility for generating Kin accounts from BIP39/Electrum seed phrases
Home-page: https://github.com/chancity/seed-phrases-for-kin
Author: chancity
Author-email: chancey@kinny.io
License: http://opensource.org/licenses/MIT
Requires-Dist: mnemonic (>=0.18)
Requires-Dist: pbkdf2 (>=1.3)
Requires-Dist: stellar-base (>=0.1.5)
Requires-Dist: toml (>=0.10.0)
